{"originalCurrency": "USD", "convertedCurrency": "USD", "report": [{"date": "2023-09-30", "symbol": "HOLX", "reportedCurrency": "USD", "cik": "0000859737", "fillingDate": "2023-11-21", "acceptedDate": "2023-11-21 08:17:06", "calendarYear": "2023", "period": "FY", "revenue": 4030400000, "costOfRevenue": 1958900000, "grossProfit": 2071500000, "grossProfitRatio": 0.5139688368, "researchAndDevelopmentExpenses": 294300000, "generalAndAdministrativeExpenses": 392400000, "sellingAndMarketingExpenses": 595200000, "sellingGeneralAndAdministrativeExpenses": 987600000, "otherExpenses": -1700000, "operatingExpenses": 1310000000, "costAndExpenses": 3268900000, "interestIncome": 120500000, "interestExpense": 111100000, "depreciationAndAmortization": 323400000, "ebitda": 1203700000, "ebitdaratio": 0.2986552203, "operatingIncome": 668400000, "operatingIncomeRatio": 0.1658396189, "totalOtherIncomeExpensesNet": -94800000, "incomeBeforeTax": 676100000, "incomeBeforeTaxRatio": 0.1677500992, "incomeTaxExpense": 220100000, "netIncome": 456000000, "netIncomeRatio": 0.113140135, "eps": 1.85, "epsdiluted": 1.83, "weightedAverageShsOut": 246772000, "weightedAverageShsOutDil": 248831000, "link": "https://www.sec.gov/Archives/edgar/data/859737/000085973723000023/0000859737-23-000023-index.htm", "finalLink": "https://www.sec.gov/Archives/edgar/data/859737/000085973723000023/holx-20230930.htm", "calculatedOtherExpenses": 121200000, "calculatedOperatingExpenses": 1403100000, "calculatedNetInterest": 9400000, "calculatedOtherIncome": -1700000, "calculatedIncomeNonControlling": 0, "calculatedEbitda": 991800000}, {"date": "2022-09-24", "symbol": "HOLX", "reportedCurrency": "USD", "cik": "0000859737", "fillingDate": "2022-11-15", "acceptedDate": "2022-11-15 08:26:06", "calendarYear": "2022", "period": "FY", "revenue": 4862800000, "costOfRevenue": 1865400000, "grossProfit": 2997400000, "grossProfitRatio": 0.6163938472, "researchAndDevelopmentExpenses": 283400000, "generalAndAdministrativeExpenses": 407700000, "sellingAndMarketingExpenses": 630300000, "sellingGeneralAndAdministrativeExpenses": 1038000000, "otherExpenses": 45200000, "operatingExpenses": 1366600000, "costAndExpenses": 3232000000, "interestIncome": 12900000, "interestExpense": 95100000, "depreciationAndAmortization": 464500000, "ebitda": 2104700000, "ebitdaratio": 0.4328164843, "operatingIncome": 1640200000, "operatingIncomeRatio": 0.3372953854, "totalOtherIncomeExpensesNet": -52000000, "incomeBeforeTax": 1588200000, "incomeBeforeTaxRatio": 0.3266019577, "incomeTaxExpense": 286200000, "netIncome": 1302000000, "netIncomeRatio": 0.2677469771, "eps": 5.18, "epsdiluted": 5.13, "weightedAverageShsOut": 251527000, "weightedAverageShsOutDil": 253845000, "link": "https://www.sec.gov/Archives/edgar/data/859737/000085973722000022/0000859737-22-000022-index.htm", "finalLink": "https://www.sec.gov/Archives/edgar/data/859737/000085973722000022/holx-20220924.htm", "calculatedOtherExpenses": 35800000, "calculatedOperatingExpenses": 1357200000, "calculatedNetInterest": -82200000, "calculatedOtherIncome": 30200000, "calculatedIncomeNonControlling": 0, "calculatedEbitda": 2104700000}, {"date": "2021-09-25", "symbol": "HOLX", "reportedCurrency": "USD", "cik": "0000859737", "fillingDate": "2021-11-16", "acceptedDate": "2021-11-16 08:36:50", "calendarYear": "2021", "period": "FY", "revenue": 5632300000, "costOfRevenue": 1836500000, "grossProfit": 3795800000, "grossProfitRatio": 0.673934272, "researchAndDevelopmentExpenses": 276300000, "generalAndAdministrativeExpenses": 433200000, "sellingAndMarketingExpenses": 561200000, "sellingGeneralAndAdministrativeExpenses": 994400000, "otherExpenses": 42200000, "operatingExpenses": 1312900000, "costAndExpenses": 3149400000, "interestIncome": 1400000, "interestExpense": 93600000, "depreciationAndAmortization": 405500000, "ebitda": 2885800000, "ebitdaratio": 0.5123661737, "operatingIncome": 2480300000, "operatingIncomeRatio": 0.4403707189, "totalOtherIncomeExpensesNet": -119200000, "incomeBeforeTax": 2361100000, "incomeBeforeTaxRatio": 0.4192070735, "incomeTaxExpense": 491400000, "netIncome": 1871500000, "netIncomeRatio": 0.3322798857, "eps": 7.28, "epsdiluted": 7.21, "weightedAverageShsOut": 257046000, "weightedAverageShsOutDil": 259706000, "link": "https://www.sec.gov/Archives/edgar/data/859737/000085973721000023/0000859737-21-000023-index.htm", "finalLink": "https://www.sec.gov/Archives/edgar/data/859737/000085973721000023/holx-20210925.htm", "calculatedOtherExpenses": 44800000, "calculatedOperatingExpenses": 1315500000, "calculatedNetInterest": -92200000, "calculatedOtherIncome": -27000000, "calculatedIncomeNonControlling": -1800000, "calculatedEbitda": 2885800000}, {"date": "2020-09-26", "symbol": "HOLX", "reportedCurrency": "USD", "cik": "0000859737", "fillingDate": "2020-11-17", "acceptedDate": "2020-11-17 08:20:30", "calendarYear": "2020", "period": "FY", "revenue": 3776400000, "costOfRevenue": 1548900000, "grossProfit": 2227500000, "grossProfitRatio": 0.5898474738, "researchAndDevelopmentExpenses": 222500000, "generalAndAdministrativeExpenses": 356000000, "sellingAndMarketingExpenses": 484600000, "sellingGeneralAndAdministrativeExpenses": 840600000, "otherExpenses": 39700000, "operatingExpenses": 1102800000, "costAndExpenses": 2651700000, "interestIncome": 4300000, "interestExpense": 116500000, "depreciationAndAmortization": 409100000, "ebitda": 1514100000, "ebitdaratio": 0.4009374007, "operatingIncome": 1105000000, "operatingIncomeRatio": 0.2926067154, "totalOtherIncomeExpensesNet": -103100000, "incomeBeforeTax": 1001900000, "incomeBeforeTaxRatio": 0.265305582, "incomeTaxExpense": -108600000, "netIncome": 1115200000, "netIncomeRatio": 0.2953077005, "eps": 4.24, "epsdiluted": 4.21, "weightedAverageShsOut": 262726999, "weightedAverageShsOutDil": 264613000, "link": "https://www.sec.gov/Archives/edgar/data/859737/000085973720000039/0000859737-20-000039-index.htm", "finalLink": "https://www.sec.gov/Archives/edgar/data/859737/000085973720000039/holx-20200926.htm", "calculatedOtherExpenses": 59400000, "calculatedOperatingExpenses": 1122500000, "calculatedNetInterest": -112200000, "calculatedOtherIncome": 9100000, "calculatedIncomeNonControlling": -4700000, "calculatedEbitda": 1514100000}, {"date": "2019-09-28", "symbol": "HOLX", "reportedCurrency": "USD", "cik": "0000859737", "fillingDate": "2019-11-27", "acceptedDate": "2019-11-27 07:48:06", "calendarYear": "2019", "period": "FY", "revenue": 3367300000, "costOfRevenue": 2059200000, "grossProfit": 1308100000, "grossProfitRatio": 0.3884714757, "researchAndDevelopmentExpenses": 232200000, "generalAndAdministrativeExpenses": 332300000, "sellingAndMarketingExpenses": 564900000, "sellingGeneralAndAdministrativeExpenses": 897200000, "otherExpenses": 52000000, "operatingExpenses": 1181400000, "costAndExpenses": 3240600000, "interestIncome": 4600000, "interestExpense": 140800000, "depreciationAndAmortization": 463100000, "ebitda": 597500000, "ebitdaratio": 0.1774418674, "operatingIncome": 134400000, "operatingIncomeRatio": 0.0399132836, "totalOtherIncomeExpensesNet": -229700000, "incomeBeforeTax": -95300000, "incomeBeforeTaxRatio": -0.0283016066, "incomeTaxExpense": -55100000, "netIncome": -40200000, "netIncomeRatio": -0.0119383482, "eps": -0.15, "epsdiluted": -0.15, "weightedAverageShsOut": 269413000, "weightedAverageShsOutDil": 269413000, "link": "https://www.sec.gov/Archives/edgar/data/859737/000085973719000026/0000859737-19-000026-index.htm", "finalLink": "https://www.sec.gov/Archives/edgar/data/859737/000085973719000026/holxq4-2019.htm", "calculatedOtherExpenses": 44300000, "calculatedOperatingExpenses": 1173700000, "calculatedNetInterest": -136200000, "calculatedOtherIncome": -93500000, "calculatedIncomeNonControlling": 0, "calculatedEbitda": 597500000}, {"date": "2018-09-29", "symbol": "HOLX", "reportedCurrency": "USD", "cik": "0000859737", "fillingDate": "2018-11-20", "acceptedDate": "2018-11-20 08:00:52", "calendarYear": "2018", "period": "FY", "revenue": 3217900000, "costOfRevenue": 1521200000, "grossProfit": 1696700000, "grossProfitRatio": 0.5272693371, "researchAndDevelopmentExpenses": 218700000, "generalAndAdministrativeExpenses": 366100000, "sellingAndMarketingExpenses": 544600000, "sellingGeneralAndAdministrativeExpenses": 910700000, "otherExpenses": 7600000, "operatingExpenses": 1188700000, "costAndExpenses": 2709900000, "interestIncome": 6300000, "interestExpense": 148700000, "depreciationAndAmortization": 480300000, "ebitda": 1002200000, "ebitdaratio": 0.3114453526, "operatingIncome": -237900000, "operatingIncomeRatio": -0.0739302029, "totalOtherIncomeExpensesNet": -784200000, "incomeBeforeTax": -418600000, "incomeBeforeTaxRatio": -0.1300848379, "incomeTaxExpense": -307300000, "netIncome": -111300000, "netIncomeRatio": -0.0345877746, "eps": -0.4, "epsdiluted": -0.4, "weightedAverageShsOut": 275105000, "weightedAverageShsOutDil": 275105000, "link": "https://www.sec.gov/Archives/edgar/data/859737/000085973718000020/0000859737-18-000020-index.htm", "finalLink": "https://www.sec.gov/Archives/edgar/data/859737/000085973718000020/holx_q4-2018.htm", "calculatedOtherExpenses": 805200000, "calculatedOperatingExpenses": 1934600000, "calculatedNetInterest": -142400000, "calculatedOtherIncome": -38300000, "calculatedIncomeNonControlling": 0, "calculatedEbitda": 242400000}, {"date": "2017-09-30", "symbol": "HOLX", "reportedCurrency": "USD", "cik": "0000859737", "fillingDate": "2017-11-21", "acceptedDate": "2017-11-21 08:54:05", "calendarYear": "2017", "period": "FY", "revenue": 3058800000, "costOfRevenue": 1437800000, "grossProfit": 1621000000, "grossProfitRatio": 0.5299463842, "researchAndDevelopmentExpenses": 232800000, "generalAndAdministrativeExpenses": 343300000, "sellingAndMarketingExpenses": 498600000, "sellingGeneralAndAdministrativeExpenses": 841900000, "otherExpenses": 12900000, "operatingExpenses": 1137200000, "costAndExpenses": 2575000000, "interestIncome": 3800000, "interestExpense": 153200000, "depreciationAndAmortization": 449200000, "ebitda": 949700000, "ebitdaratio": 0.3104812345, "operatingIncome": 1370200000, "operatingIncomeRatio": 0.4479534458, "totalOtherIncomeExpensesNet": 896100000, "incomeBeforeTax": 1230500000, "incomeBeforeTaxRatio": 0.4022819406, "incomeTaxExpense": 475000000, "netIncome": 755500000, "netIncomeRatio": 0.2469922846, "eps": 2.7, "epsdiluted": 2.64, "weightedAverageShsOut": 279811000, "weightedAverageShsOutDil": 285653000, "link": "https://www.sec.gov/Archives/edgar/data/859737/000085973717000023/0000859737-17-000023-index.htm", "finalLink": "https://www.sec.gov/Archives/edgar/data/859737/000085973717000023/holx_q4-2017.htm", "calculatedOtherExpenses": -823900000, "calculatedOperatingExpenses": 250800000, "calculatedNetInterest": -149400000, "calculatedOtherIncome": 9700000, "calculatedIncomeNonControlling": 0, "calculatedEbitda": 1819400000}, {"date": "2016-09-24", "symbol": "HOLX", "reportedCurrency": "USD", "cik": "0000859737", "fillingDate": "2016-11-17", "acceptedDate": "2016-11-17 06:23:23", "calendarYear": "2016", "period": "FY", "revenue": 2832700000, "costOfRevenue": 1269400000, "grossProfit": 1563300000, "grossProfitRatio": 0.5518763018, "researchAndDevelopmentExpenses": 232100000, "generalAndAdministrativeExpenses": 267300000, "sellingAndMarketingExpenses": 415100000, "sellingGeneralAndAdministrativeExpenses": 682400000, "otherExpenses": 26600000, "operatingExpenses": 1004200000, "costAndExpenses": 2273600000, "interestIncome": 700000, "interestExpense": 155300000, "depreciationAndAmortization": 465400000, "ebitda": 1051800000, "ebitdaratio": 0.3713065273, "operatingIncome": 548600000, "operatingIncomeRatio": 0.1936668196, "totalOtherIncomeExpensesNet": 10800000, "incomeBeforeTax": 415300000, "incomeBeforeTaxRatio": 0.1466092421, "incomeTaxExpense": 84500000, "netIncome": 330800000, "netIncomeRatio": 0.1167790447, "eps": 1.18, "epsdiluted": 1.16, "weightedAverageShsOut": 280213000, "weightedAverageShsOutDil": 286156000, "link": "https://www.sec.gov/Archives/edgar/data/859737/000085973716000071/0000859737-16-000071-index.htm", "finalLink": "https://www.sec.gov/Archives/edgar/data/859737/000085973716000071/holx_q4-2016.htm", "calculatedOtherExpenses": 100200000, "calculatedOperatingExpenses": 1014700000, "calculatedNetInterest": -154600000, "calculatedOtherIncome": 21300000, "calculatedIncomeNonControlling": 0, "calculatedEbitda": 1014000000}, {"date": "2015-09-26", "symbol": "HOLX", "reportedCurrency": "USD", "cik": "0000859737", "fillingDate": "2015-11-19", "acceptedDate": "2015-11-19 06:31:19", "calendarYear": "2015", "period": "FY", "revenue": 2705000000, "costOfRevenue": 1272300000, "grossProfit": 1432700000, "grossProfitRatio": 0.5296487985, "researchAndDevelopmentExpenses": 214900000, "generalAndAdministrativeExpenses": 261000000, "sellingAndMarketingExpenses": 363000000, "sellingGeneralAndAdministrativeExpenses": 624000000, "otherExpenses": -11000000, "operatingExpenses": 949100000, "costAndExpenses": 2221400000, "interestIncome": 1300000, "interestExpense": 205500000, "depreciationAndAmortization": 491400000, "ebitda": 965300000, "ebitdaratio": 0.356857671, "operatingIncome": 455100000, "operatingIncomeRatio": 0.1682439926, "totalOtherIncomeExpensesNet": -102200000, "incomeBeforeTax": 177200000, "incomeBeforeTaxRatio": 0.0655083179, "incomeTaxExpense": 45600000, "netIncome": 131600000, "netIncomeRatio": 0.048650647, "eps": 0.47, "epsdiluted": 0.45, "weightedAverageShsOut": 280566000, "weightedAverageShsOutDil": 289537000, "link": "https://www.sec.gov/Archives/edgar/data/859737/000085973715000034/0000859737-15-000034-index.htm", "finalLink": "https://www.sec.gov/Archives/edgar/data/859737/000085973715000034/holx_q4-2015.htm", "calculatedOtherExpenses": 138700000, "calculatedOperatingExpenses": 977600000, "calculatedNetInterest": -204200000, "calculatedOtherIncome": -73700000, "calculatedIncomeNonControlling": 0, "calculatedEbitda": 946500000}, {"date": "2014-09-27", "symbol": "HOLX", "reportedCurrency": "USD", "cik": "0000859737", "fillingDate": "2014-11-20", "acceptedDate": "2014-11-20 07:00:54", "calendarYear": "2014", "period": "FY", "revenue": 2530700000, "costOfRevenue": 1285200000, "grossProfit": 1245500000, "grossProfitRatio": 0.4921563204, "researchAndDevelopmentExpenses": 203200000, "generalAndAdministrativeExpenses": 259800000, "sellingAndMarketingExpenses": 331700000, "sellingGeneralAndAdministrativeExpenses": 591500000, "otherExpenses": -3600000, "operatingExpenses": 908500000, "costAndExpenses": 2193700000, "interestIncome": 1300000, "interestExpense": 220600000, "depreciationAndAmortization": 113800000, "ebitda": 447200000, "ebitdaratio": 0.1767100012, "operatingIncome": 279700000, "operatingIncomeRatio": 0.1105227803, "totalOtherIncomeExpensesNet": -68300000, "incomeBeforeTax": 48100000, "incomeBeforeTaxRatio": 0.019006599, "incomeTaxExpense": 30800000, "netIncome": 17300000, "netIncomeRatio": 0.0068360533, "eps": 0.06, "epsdiluted": 0.06, "weightedAverageShsOut": 275499000, "weightedAverageShsOutDil": 278360000, "link": "https://www.sec.gov/Archives/edgar/data/859737/000085973714000008/0000859737-14-000008-index.htm", "finalLink": "https://www.sec.gov/Archives/edgar/data/859737/000085973714000008/holx_q4-2014.htm", "calculatedOtherExpenses": 171100000, "calculatedOperatingExpenses": 965800000, "calculatedNetInterest": -219300000, "calculatedOtherIncome": -12300000, "calculatedIncomeNonControlling": 0, "calculatedEbitda": 393500000}, {"date": "2013-09-28", "symbol": "HOLX", "reportedCurrency": "USD", "cik": "0000859737", "fillingDate": "2013-11-26", "acceptedDate": "2013-11-26 06:43:20", "calendarYear": "2013", "period": "FY", "revenue": 2492279000, "costOfRevenue": 1330891000, "grossProfit": 1161388000, "grossProfitRatio": 0.465994377, "researchAndDevelopmentExpenses": 197646000, "generalAndAdministrativeExpenses": 227680000, "sellingAndMarketingExpenses": 342137000, "sellingGeneralAndAdministrativeExpenses": 569817000, "otherExpenses": 3605000, "operatingExpenses": 880060000, "costAndExpenses": 2210951000, "interestIncome": 1302000, "interestExpense": 281075000, "depreciationAndAmortization": 112597000, "ebitda": 397530000, "ebitdaratio": 0.1595046141, "operatingIncome": -906282000, "operatingIncomeRatio": -0.363635853, "totalOtherIncomeExpensesNet": -1193214000, "incomeBeforeTax": -1192961000, "incomeBeforeTaxRatio": -0.4786627019, "incomeTaxExpense": -20123000, "netIncome": -1172838000, "netIncomeRatio": -0.4705885657, "eps": -4.36, "epsdiluted": -4.36, "weightedAverageShsOut": 268704000, "weightedAverageShsOutDil": 268704000, "link": "https://www.sec.gov/Archives/edgar/data/859737/000119312513453681/0001193125-13-453681-index.htm", "finalLink": "https://www.sec.gov/Archives/edgar/data/859737/000119312513453681/d592931d10k.htm", "calculatedOtherExpenses": 1300207000, "calculatedOperatingExpenses": 2067670000, "calculatedNetInterest": -279773000, "calculatedOtherIncome": -6906000, "calculatedIncomeNonControlling": 0, "calculatedEbitda": -793685000}, {"date": "2012-09-29", "symbol": "HOLX", "reportedCurrency": "USD", "cik": "0000859737", "fillingDate": "2012-11-28", "acceptedDate": "2012-11-28 07:31:27", "calendarYear": "2012", "period": "FY", "revenue": 2002652000, "costOfRevenue": 1008215000, "grossProfit": 994437000, "grossProfitRatio": 0.4965600614, "researchAndDevelopmentExpenses": 130962000, "generalAndAdministrativeExpenses": 220042000, "sellingAndMarketingExpenses": 322314000, "sellingGeneralAndAdministrativeExpenses": 542356000, "otherExpenses": 7256000, "operatingExpenses": 745806000, "costAndExpenses": 1754021000, "interestIncome": 2340000, "interestExpense": 140287000, "depreciationAndAmortization": 72036000, "ebitda": 327923000, "ebitdaratio": 0.163744375, "operatingIncome": 113717000, "operatingIncomeRatio": 0.0567832055, "totalOtherIncomeExpensesNet": -170005000, "incomeBeforeTax": -61661000, "incomeBeforeTaxRatio": -0.0307896729, "incomeTaxExpense": 11973000, "netIncome": -73634000, "netIncomeRatio": -0.0367682453, "eps": -0.28, "epsdiluted": -0.28, "weightedAverageShsOut": 262857142, "weightedAverageShsOutDil": 264041000, "link": "https://www.sec.gov/Archives/edgar/data/859737/000119312512482840/0001193125-12-482840-index.htm", "finalLink": "https://www.sec.gov/Archives/edgar/data/859737/000119312512482840/d393079d10k.htm", "calculatedOtherExpenses": 207402000, "calculatedOperatingExpenses": 880720000, "calculatedNetInterest": -137947000, "calculatedOtherIncome": -37431000, "calculatedIncomeNonControlling": 0, "calculatedEbitda": 185753000}, {"date": "2011-09-24", "symbol": "HOLX", "reportedCurrency": "USD", "cik": "0000859737", "fillingDate": "2011-11-23", "acceptedDate": "2011-11-23 09:21:44", "calendarYear": "2011", "period": "FY", "revenue": 1789349000, "costOfRevenue": 866168000, "grossProfit": 923181000, "grossProfitRatio": 0.515931213, "researchAndDevelopmentExpenses": 116696000, "generalAndAdministrativeExpenses": 158793000, "sellingAndMarketingExpenses": 286730000, "sellingGeneralAndAdministrativeExpenses": 445523000, "otherExpenses": -4182000, "operatingExpenses": 536051000, "costAndExpenses": 1402219000, "interestIncome": 1860000, "interestExpense": 114846000, "depreciationAndAmortization": 58334000, "ebitda": 490362000, "ebitdaratio": 0.274044918, "operatingIncome": 374445000, "operatingIncomeRatio": 0.2092632572, "totalOtherIncomeExpensesNet": -44898000, "incomeBeforeTax": 227386000, "incomeBeforeTaxRatio": 0.1270775014, "incomeTaxExpense": 70236000, "netIncome": 157150000, "netIncomeRatio": 0.087825237, "eps": 0.6, "epsdiluted": 0.59, "weightedAverageShsOut": 261099000, "weightedAverageShsOutDil": 264305000, "link": "https://www.sec.gov/Archives/edgar/data/859737/000119312511320641/0001193125-11-320641-index.htm", "finalLink": "https://www.sec.gov/Archives/edgar/data/859737/000119312511320641/d229330d10k.htm", "calculatedOtherExpenses": -13483000, "calculatedOperatingExpenses": 548736000, "calculatedNetInterest": -112986000, "calculatedOtherIncome": -34073000, "calculatedIncomeNonControlling": 0, "calculatedEbitda": 432779000}, {"date": "2010-09-25", "symbol": "HOLX", "reportedCurrency": "USD", "cik": "0000859737", "fillingDate": "2010-11-24", "acceptedDate": "2010-11-24 07:30:49", "calendarYear": "2010", "period": "FY", "revenue": 1679552000, "costOfRevenue": 942914000, "grossProfit": 736638000, "grossProfitRatio": 0.4385919579, "researchAndDevelopmentExpenses": 104305000, "generalAndAdministrativeExpenses": 159743000, "sellingAndMarketingExpenses": 247374000, "sellingGeneralAndAdministrativeExpenses": 407117000, "otherExpenses": 901000, "operatingExpenses": 566280000, "costAndExpenses": 1509194000, "interestIncome": 1278000, "interestExpense": 126206000, "depreciationAndAmortization": 54858000, "ebitda": 226494000, "ebitdaratio": 0.1348538182, "operatingIncome": 69937000, "operatingIncomeRatio": 0.0416402707, "totalOtherIncomeExpensesNet": -100421000, "incomeBeforeTax": -54991000, "incomeBeforeTaxRatio": -0.0327414692, "incomeTaxExpense": 7822000, "netIncome": -62813000, "netIncomeRatio": -0.0373986635, "eps": -0.24, "epsdiluted": -0.24, "weightedAverageShsOut": 258743000, "weightedAverageShsOutDil": 258743000, "link": "https://www.sec.gov/Archives/edgar/data/859737/000119312510268147/0001193125-10-268147-index.htm", "finalLink": "https://www.sec.gov/Archives/edgar/data/859737/000119312510268147/d10k.htm", "calculatedOtherExpenses": 155279000, "calculatedOperatingExpenses": 666701000, "calculatedNetInterest": -124928000, "calculatedOtherIncome": 0, "calculatedIncomeNonControlling": 0, "calculatedEbitda": 124795000}, {"date": "2009-09-26", "symbol": "HOLX", "reportedCurrency": "USD", "cik": "0000859737", "fillingDate": "2009-11-24", "acceptedDate": "2009-11-24 16:06:57", "calendarYear": "2009", "period": "FY", "revenue": 1637134000, "costOfRevenue": 779648000, "grossProfit": 857486000, "grossProfitRatio": 0.5237726417, "researchAndDevelopmentExpenses": 94328000, "generalAndAdministrativeExpenses": 148825000, "sellingAndMarketingExpenses": 238977000, "sellingGeneralAndAdministrativeExpenses": 387802000, "otherExpenses": 0, "operatingExpenses": 533340000, "costAndExpenses": 1312988000, "interestIncome": 1161000, "interestExpense": 73162000, "depreciationAndAmortization": 51210000, "ebitda": 376517000, "ebitdaratio": 0.2299854502, "operatingIncome": -2016674000, "operatingIncomeRatio": -1.2318319698, "totalOtherIncomeExpensesNet": -2340820000, "incomeBeforeTax": -2088675000, "incomeBeforeTaxRatio": -1.2758118761, "incomeTaxExpense": 87562000, "netIncome": -2176237000, "netIncomeRatio": -1.3292968077, "eps": -8.48, "epsdiluted": -8.48, "weightedAverageShsOut": 256545000, "weightedAverageShsOutDil": 256545000, "link": "https://www.sec.gov/Archives/edgar/data/859737/000119312509241357/0001193125-09-241357-index.htm", "finalLink": "https://www.sec.gov/Archives/edgar/data/859737/000119312509241357/d10k.htm", "calculatedOtherExpenses": 2392030000, "calculatedOperatingExpenses": 2874160000, "calculatedNetInterest": -72001000, "calculatedOtherIncome": 0, "calculatedIncomeNonControlling": 0, "calculatedEbitda": -1965464000}, {"date": "2008-09-27", "symbol": "HOLX", "reportedCurrency": "USD", "cik": "0000859737", "fillingDate": "2008-11-26", "acceptedDate": "2008-11-26 15:49:51", "calendarYear": "2008", "period": "FY", "revenue": 1674499000, "costOfRevenue": 781981000, "grossProfit": 892518000, "grossProfitRatio": 0.5330059916, "researchAndDevelopmentExpenses": 81421000, "generalAndAdministrativeExpenses": 147405000, "sellingAndMarketingExpenses": 261524000, "sellingGeneralAndAdministrativeExpenses": 408929000, "otherExpenses": 0, "operatingExpenses": 518477000, "costAndExpenses": 1300458000, "interestIncome": 4528000, "interestExpense": 84912000, "depreciationAndAmortization": 172950000, "ebitda": 1122689000, "ebitdaratio": 0.6704626279, "operatingIncome": -197542000, "operatingIncomeRatio": -0.117970808, "totalOtherIncomeExpensesNet": -575698000, "incomeBeforeTax": -279141000, "incomeBeforeTaxRatio": -0.1667012044, "incomeTaxExpense": 106476000, "netIncome": -385617000, "netIncomeRatio": -0.2302879846, "eps": -1.57, "epsdiluted": -1.57, "weightedAverageShsOut": 245968000, "weightedAverageShsOutDil": 245968000, "link": "https://www.sec.gov/Archives/edgar/data/859737/000119312508244529/0001193125-08-244529-index.htm", "finalLink": "https://www.sec.gov/Archives/edgar/data/859737/000119312508244529/d10k.htm", "calculatedOtherExpenses": 599710000, "calculatedOperatingExpenses": 1090060000, "calculatedNetInterest": -80384000, "calculatedOtherIncome": -1215000, "calculatedIncomeNonControlling": 0, "calculatedEbitda": -24592000}, {"date": "2007-09-29", "symbol": "HOLX", "reportedCurrency": "USD", "cik": "0000859737", "fillingDate": "2007-11-27", "acceptedDate": "2007-11-27 15:43:12", "calendarYear": "2007", "period": "FY", "revenue": 738368000, "costOfRevenue": 392801000, "grossProfit": 345567000, "grossProfitRatio": 0.4680145943, "researchAndDevelopmentExpenses": 44484000, "generalAndAdministrativeExpenses": 0, "sellingAndMarketingExpenses": 0, "sellingGeneralAndAdministrativeExpenses": 147747000, "otherExpenses": 0, "operatingExpenses": 197815000, "costAndExpenses": 590616000, "interestIncome": 0, "interestExpense": 0, "depreciationAndAmortization": 31162000, "ebitda": 178914000, "ebitdaratio": 0.2423100676, "operatingIncome": 147752000, "operatingIncomeRatio": 0.2001061801, "totalOtherIncomeExpensesNet": 737000, "incomeBeforeTax": 148489000, "incomeBeforeTaxRatio": 0.2011043274, "incomeTaxExpense": 53911000, "netIncome": 94578000, "netIncomeRatio": 0.1280905998, "eps": 0.88, "epsdiluted": 0.86, "weightedAverageShsOut": 106873000, "weightedAverageShsOutDil": 109669000, "link": "https://www.sec.gov/Archives/edgar/data/859737/000119312507253993/0001193125-07-253993-index.htm", "finalLink": "https://www.sec.gov/Archives/edgar/data/859737/000119312507253993/d10k.htm", "calculatedOtherExpenses": 5584000, "calculatedOperatingExpenses": 197815000, "calculatedNetInterest": 0, "calculatedOtherIncome": 737000, "calculatedIncomeNonControlling": 0, "calculatedEbitda": 178914000}, {"date": "2006-09-30", "symbol": "HOLX", "reportedCurrency": "USD", "cik": "0000859737", "fillingDate": "2006-12-14", "acceptedDate": "2006-12-14 16:04:57", "calendarYear": "2006", "period": "FY", "revenue": 462680000, "costOfRevenue": 269148000, "grossProfit": 193532000, "grossProfitRatio": 0.4182847757, "researchAndDevelopmentExpenses": 28294000, "generalAndAdministrativeExpenses": 42551000, "sellingAndMarketingExpenses": 55910000, "sellingGeneralAndAdministrativeExpenses": 98461000, "otherExpenses": 0, "operatingExpenses": 123293000, "costAndExpenses": 392441000, "interestIncome": 4082000, "interestExpense": -1198000, "depreciationAndAmortization": 16133000, "ebitda": 101179000, "ebitdaratio": 0.2186802974, "operatingIncome": 50339000, "operatingIncomeRatio": 0.1087987378, "totalOtherIncomeExpensesNet": -14807000, "incomeBeforeTax": 53223000, "incomeBeforeTaxRatio": 0.1150319876, "incomeTaxExpense": 25800000, "netIncome": 27423000, "netIncomeRatio": 0.0592699058, "eps": 0.3, "epsdiluted": 0.28, "weightedAverageShsOut": 93024000, "weightedAverageShsOutDil": 97240000, "link": "https://www.sec.gov/Archives/edgar/data/859737/000119312506253369/0001193125-06-253369-index.htm", "finalLink": "https://www.sec.gov/Archives/edgar/data/859737/000119312506253369/d10k.htm", "calculatedOtherExpenses": 16438000, "calculatedOperatingExpenses": 143193000, "calculatedNetInterest": 5280000, "calculatedOtherIncome": -2396000, "calculatedIncomeNonControlling": 0, "calculatedEbitda": 66472000}, {"date": "2005-09-24", "symbol": "HOLX", "reportedCurrency": "USD", "cik": "0000859737", "fillingDate": "2005-12-06", "acceptedDate": "2005-12-06 09:02:42", "calendarYear": "2005", "period": "FY", "revenue": 287684000, "costOfRevenue": 174659000, "grossProfit": 113025000, "grossProfitRatio": 0.3928789922, "researchAndDevelopmentExpenses": 18617000, "generalAndAdministrativeExpenses": 27578000, "sellingAndMarketingExpenses": 34199000, "sellingGeneralAndAdministrativeExpenses": 61777000, "otherExpenses": 0, "operatingExpenses": 80394000, "costAndExpenses": 255053000, "interestIncome": 2219000, "interestExpense": -155000, "depreciationAndAmortization": 7574000, "ebitda": 40205000, "ebitdaratio": 0.1397540357, "operatingIncome": 32631000, "operatingIncomeRatio": 0.1134265375, "totalOtherIncomeExpensesNet": 2064000, "incomeBeforeTax": 34695000, "incomeBeforeTaxRatio": 0.1206010762, "incomeTaxExpense": 6439000, "netIncome": 28256000, "netIncomeRatio": 0.098218879, "eps": 0.33, "epsdiluted": 0.32, "weightedAverageShsOut": 85648000, "weightedAverageShsOutDil": 90252000, "link": "https://www.sec.gov/Archives/edgar/data/859737/000119312505237204/0001193125-05-237204-index.htm", "finalLink": "https://www.sec.gov/Archives/edgar/data/859737/000119312505237204/d10k.htm", "calculatedOtherExpenses": 0, "calculatedOperatingExpenses": 80394000, "calculatedNetInterest": 2374000, "calculatedOtherIncome": -310000, "calculatedIncomeNonControlling": 0, "calculatedEbitda": 40205000}, {"date": "2004-09-25", "symbol": "HOLX", "reportedCurrency": "USD", "cik": "0000859737", "fillingDate": "2004-12-08", "acceptedDate": "2004-12-08 17:03:02", "calendarYear": "2004", "period": "FY", "revenue": 228705000, "costOfRevenue": 143336000, "grossProfit": 85369000, "grossProfitRatio": 0.3732712446, "researchAndDevelopmentExpenses": 16659000, "generalAndAdministrativeExpenses": 24363000, "sellingAndMarketingExpenses": 31761000, "sellingGeneralAndAdministrativeExpenses": 56124000, "otherExpenses": 0, "operatingExpenses": 72783000, "costAndExpenses": 216119000, "interestIncome": 540000, "interestExpense": -199000, "depreciationAndAmortization": 7589000, "ebitda": 20175000, "ebitdaratio": 0.0882140749, "operatingIncome": 12586000, "operatingIncomeRatio": 0.0550315909, "totalOtherIncomeExpensesNet": 341000, "incomeBeforeTax": 12927000, "incomeBeforeTaxRatio": 0.0565225946, "incomeTaxExpense": 763000, "netIncome": 12164000, "netIncomeRatio": 0.0531864192, "eps": 0.15, "epsdiluted": 0.14, "weightedAverageShsOut": 81032000, "weightedAverageShsOutDil": 85186000, "link": "https://www.sec.gov/Archives/edgar/data/859737/000119312504209557/0001193125-04-209557-index.htm", "finalLink": "https://www.sec.gov/Archives/edgar/data/859737/000119312504209557/d10k.htm", "calculatedOtherExpenses": 0, "calculatedOperatingExpenses": 72783000, "calculatedNetInterest": 739000, "calculatedOtherIncome": -398000, "calculatedIncomeNonControlling": 0, "calculatedEbitda": 20175000}, {"date": "2003-09-27", "symbol": "HOLX", "reportedCurrency": "USD", "cik": "0000859737", "fillingDate": "2003-12-23", "acceptedDate": "2003-12-23 15:49:14", "calendarYear": "2003", "period": "FY", "revenue": 204035000, "costOfRevenue": 130455000, "grossProfit": 73580000, "grossProfitRatio": 0.3606244027, "researchAndDevelopmentExpenses": 18381000, "generalAndAdministrativeExpenses": 0, "sellingAndMarketingExpenses": 0, "sellingGeneralAndAdministrativeExpenses": 52174000, "otherExpenses": 0, "operatingExpenses": 70555000, "costAndExpenses": 201010000, "interestIncome": 0, "interestExpense": 0, "depreciationAndAmortization": 7405000, "ebitda": 10430000, "ebitdaratio": 0.0511186806, "operatingIncome": 3025000, "operatingIncomeRatio": 0.0148258877, "totalOtherIncomeExpensesNet": 240000, "incomeBeforeTax": 3265000, "incomeBeforeTaxRatio": 0.0160021565, "incomeTaxExpense": 176000, "netIncome": 2882000, "netIncomeRatio": 0.0141250276, "eps": 0.0375, "epsdiluted": 0.035, "weightedAverageShsOut": 78516000, "weightedAverageShsOutDil": 80520000, "link": "https://www.sec.gov/Archives/edgar/data/859737/000119312503098850/0001193125-03-098850-index.htm", "finalLink": "https://www.sec.gov/Archives/edgar/data/859737/000119312503098850/d10k.htm", "calculatedOtherExpenses": 0, "calculatedOperatingExpenses": 70555000, "calculatedNetInterest": 0, "calculatedOtherIncome": 240000, "calculatedIncomeNonControlling": 207000, "calculatedEbitda": 10430000}, {"date": "2002-09-28", "symbol": "HOLX", "reportedCurrency": "USD", "cik": "0000859737", "fillingDate": "2002-12-24", "acceptedDate": "2002-12-24 08:11:22", "calendarYear": "2002", "period": "FY", "revenue": 190192000, "costOfRevenue": 118376000, "grossProfit": 71816000, "grossProfitRatio": 0.3775973753, "researchAndDevelopmentExpenses": 20362000, "generalAndAdministrativeExpenses": 0, "sellingAndMarketingExpenses": 0, "sellingGeneralAndAdministrativeExpenses": 47227000, "otherExpenses": 0, "operatingExpenses": 67589000, "costAndExpenses": 185965000, "interestIncome": 0, "interestExpense": 0, "depreciationAndAmortization": 7476000, "ebitda": 13773000, "ebitdaratio": 0.0724162951, "operatingIncome": 2157000, "operatingIncomeRatio": 0.011341171, "totalOtherIncomeExpensesNet": -2070000, "incomeBeforeTax": -250000, "incomeBeforeTaxRatio": -0.0013144612, "incomeTaxExpense": -429000, "netIncome": 179000, "netIncomeRatio": 0.0009411542, "eps": 0.0025, "epsdiluted": 0.0025, "weightedAverageShsOut": 73676000, "weightedAverageShsOutDil": 76768000, "link": "https://www.sec.gov/Archives/edgar/data/859737/000102140802015499/0001021408-02-015499-index.htm", "finalLink": "https://www.sec.gov/Archives/edgar/data/859737/000102140802015499/d10k.txt", "calculatedOtherExpenses": 2070000, "calculatedOperatingExpenses": 69659000, "calculatedNetInterest": 0, "calculatedOtherIncome": -2407000, "calculatedIncomeNonControlling": 0, "calculatedEbitda": 9633000}, {"date": "2001-09-29", "symbol": "HOLX", "reportedCurrency": "USD", "cik": "0000859737", "fillingDate": "2001-12-12", "acceptedDate": "2001-12-12 00:00:00", "calendarYear": "2001", "period": "FY", "revenue": 178491000, "costOfRevenue": 116177000, "grossProfit": 62314000, "grossProfitRatio": 0.3491156417, "researchAndDevelopmentExpenses": 23328000, "generalAndAdministrativeExpenses": 0, "sellingAndMarketingExpenses": 0, "sellingGeneralAndAdministrativeExpenses": 56274000, "otherExpenses": 0, "operatingExpenses": 79602000, "costAndExpenses": 195779000, "interestIncome": 0, "interestExpense": 0, "depreciationAndAmortization": 8735000, "ebitda": -7035000, "ebitdaratio": -0.039413752, "operatingIncome": -18806000, "operatingIncomeRatio": -0.1053610546, "totalOtherIncomeExpensesNet": -1518000, "incomeBeforeTax": -20681000, "incomeBeforeTaxRatio": -0.1158657859, "incomeTaxExpense": 169000, "netIncome": -20850000, "netIncomeRatio": -0.1168126124, "eps": -0.34, "epsdiluted": -0.34, "weightedAverageShsOut": 61898000, "weightedAverageShsOutDil": 61898000, "link": "https://www.sec.gov/Archives/edgar/data/859737/000092701601504222/0000927016-01-504222-index.htm", "finalLink": "https://www.sec.gov/Archives/edgar/data/859737/000092701601504222/d10k405.txt", "calculatedOtherExpenses": 1518000, "calculatedOperatingExpenses": 81120000, "calculatedNetInterest": 0, "calculatedOtherIncome": -1875000, "calculatedIncomeNonControlling": 0, "calculatedEbitda": -10071000}, {"date": "2000-09-30", "symbol": "HOLX", "reportedCurrency": "USD", "cik": "0000859737", "fillingDate": "2000-12-22", "acceptedDate": "2000-12-22 00:00:00", "calendarYear": "2000", "period": "FY", "revenue": 93746000, "costOfRevenue": 59184000, "grossProfit": 34562000, "grossProfitRatio": 0.3686770636, "researchAndDevelopmentExpenses": 17178000, "generalAndAdministrativeExpenses": 0, "sellingAndMarketingExpenses": 0, "sellingGeneralAndAdministrativeExpenses": 40323000, "otherExpenses": 0, "operatingExpenses": 61921000, "costAndExpenses": 121105000, "interestIncome": 0, "interestExpense": 0, "depreciationAndAmortization": 4420000, "ebitda": -17712000, "ebitdaratio": -0.1889360613, "operatingIncome": -27359000, "operatingIncomeRatio": -0.2918417852, "totalOtherIncomeExpensesNet": -5227000, "incomeBeforeTax": -29019000, "incomeBeforeTaxRatio": -0.3095492074, "incomeTaxExpense": -10400000, "netIncome": -18619000, "netIncomeRatio": -0.1986111407, "eps": -0.3, "epsdiluted": -0.3, "weightedAverageShsOut": 61280000, "weightedAverageShsOutDil": 61280000, "link": "https://www.sec.gov/Archives/edgar/data/859737/000092701600004463/0000927016-00-004463-index.htm", "finalLink": "https://www.sec.gov/Archives/edgar/data/859737/000092701600004463/0000927016-00-004463-0001.txt", "calculatedOtherExpenses": 4420000, "calculatedOperatingExpenses": 61921000, "calculatedNetInterest": 0, "calculatedOtherIncome": -1660000, "calculatedIncomeNonControlling": 0, "calculatedEbitda": -22939000}, {"date": "1999-09-25", "symbol": "HOLX", "reportedCurrency": "USD", "cik": "0000859737", "fillingDate": "1999-12-23", "acceptedDate": "1999-12-23 00:00:00", "calendarYear": "1999", "period": "FY", "revenue": 84100000, "costOfRevenue": 46800000, "grossProfit": 37300000, "grossProfitRatio": 0.4435196195, "researchAndDevelopmentExpenses": 12700000, "generalAndAdministrativeExpenses": 0, "sellingAndMarketingExpenses": 0, "sellingGeneralAndAdministrativeExpenses": 30700000, "otherExpenses": 0, "operatingExpenses": 46900000, "costAndExpenses": 93700000, "interestIncome": 0, "interestExpense": 0, "depreciationAndAmortization": 3500000, "ebitda": -5600000, "ebitdaratio": -0.066587396, "operatingIncome": -9600000, "operatingIncomeRatio": -0.1141498216, "totalOtherIncomeExpensesNet": -500000, "incomeBeforeTax": -5800000, "incomeBeforeTaxRatio": -0.0689655172, "incomeTaxExpense": -2100000, "netIncome": -3700000, "netIncomeRatio": -0.0439952438, "eps": -0.065, "epsdiluted": -0.065, "weightedAverageShsOut": 56923077, "weightedAverageShsOutDil": 56923077, "link": "https://www.sec.gov/Archives/edgar/data/859737/000092701699004009/0000927016-99-004009-index.html", "finalLink": "https://www.sec.gov/Archives/edgar/data/859737/000092701699004009/", "calculatedOtherExpenses": 3500000, "calculatedOperatingExpenses": 46900000, "calculatedNetInterest": 0, "calculatedOtherIncome": 3800000, "calculatedIncomeNonControlling": 0, "calculatedEbitda": -6100000}, {"date": "1998-09-26", "symbol": "HOLX", "reportedCurrency": "USD", "cik": "0000859737", "fillingDate": "1998-12-23", "acceptedDate": "1998-12-23 00:00:00", "calendarYear": "1998", "period": "FY", "revenue": 115600000, "costOfRevenue": 54000000, "grossProfit": 61600000, "grossProfitRatio": 0.5328719723, "researchAndDevelopmentExpenses": 9800000, "generalAndAdministrativeExpenses": 0, "sellingAndMarketingExpenses": 0, "sellingGeneralAndAdministrativeExpenses": 39100000, "otherExpenses": 0, "operatingExpenses": 50800000, "costAndExpenses": 104800000, "interestIncome": 0, "interestExpense": 0, "depreciationAndAmortization": 1900000, "ebitda": 7400000, "ebitdaratio": 0.0640138408, "operatingIncome": 10800000, "operatingIncomeRatio": 0.0934256055, "totalOtherIncomeExpensesNet": 5300000, "incomeBeforeTax": 16200000, "incomeBeforeTaxRatio": 0.1401384083, "incomeTaxExpense": 5800000, "netIncome": 10400000, "netIncomeRatio": 0.0899653979, "eps": 0.2, "epsdiluted": 0.19, "weightedAverageShsOut": 53333333, "weightedAverageShsOutDil": 55466667, "link": "https://www.sec.gov/Archives/edgar/data/859737/000092701698004351/0000927016-98-004351-index.html", "finalLink": "https://www.sec.gov/Archives/edgar/data/859737/", "calculatedOtherExpenses": 1900000, "calculatedOperatingExpenses": 50800000, "calculatedNetInterest": 0, "calculatedOtherIncome": 5400000, "calculatedIncomeNonControlling": 0, "calculatedEbitda": 12700000}, {"date": "1997-09-27", "symbol": "HOLX", "reportedCurrency": "USD", "cik": "0000859737", "fillingDate": "1997-12-23", "acceptedDate": "1997-12-23 00:00:00", "calendarYear": "1997", "period": "FY", "revenue": 106700000, "costOfRevenue": 46200000, "grossProfit": 60500000, "grossProfitRatio": 0.5670103093, "researchAndDevelopmentExpenses": 8500000, "generalAndAdministrativeExpenses": 0, "sellingAndMarketingExpenses": 0, "sellingGeneralAndAdministrativeExpenses": 28300000, "otherExpenses": 0, "operatingExpenses": 38100000, "costAndExpenses": 84300000, "interestIncome": 0, "interestExpense": 0, "depreciationAndAmortization": 1300000, "ebitda": 18500000, "ebitdaratio": 0.1733833177, "operatingIncome": 22400000, "operatingIncomeRatio": 0.2099343955, "totalOtherIncomeExpensesNet": 5200000, "incomeBeforeTax": 27500000, "incomeBeforeTaxRatio": 0.2577319588, "incomeTaxExpense": 9800000, "netIncome": 17700000, "netIncomeRatio": 0.1658856607, "eps": 0.34, "epsdiluted": 0.33, "weightedAverageShsOut": 51678832, "weightedAverageShsOutDil": 54461538, "link": "https://www.sec.gov/Archives/edgar/data/859737/000092701697003452/0000927016-97-003452-index.html", "finalLink": "https://www.sec.gov/Archives/edgar/data/859737/", "calculatedOtherExpenses": 1300000, "calculatedOperatingExpenses": 38100000, "calculatedNetInterest": 0, "calculatedOtherIncome": 5100000, "calculatedIncomeNonControlling": 0, "calculatedEbitda": 23700000}, {"date": "1996-09-28", "symbol": "HOLX", "reportedCurrency": "USD", "cik": "0000859737", "fillingDate": "1996-12-27", "acceptedDate": "1996-12-27 00:00:00", "calendarYear": "1996", "period": "FY", "revenue": 88200000, "costOfRevenue": 40400000, "grossProfit": 47800000, "grossProfitRatio": 0.5419501134, "researchAndDevelopmentExpenses": 7300000, "generalAndAdministrativeExpenses": 0, "sellingAndMarketingExpenses": 0, "sellingGeneralAndAdministrativeExpenses": 34800000, "otherExpenses": 0, "operatingExpenses": 35700000, "costAndExpenses": 76100000, "interestIncome": 0, "interestExpense": 0, "depreciationAndAmortization": 900000, "ebitda": 8100000, "ebitdaratio": 0.0918367347, "operatingIncome": 12100000, "operatingIncomeRatio": 0.1371882086, "totalOtherIncomeExpensesNet": 4900000, "incomeBeforeTax": 17100000, "incomeBeforeTaxRatio": 0.193877551, "incomeTaxExpense": 5700000, "netIncome": 11400000, "netIncomeRatio": 0.1292517007, "eps": 0.24, "epsdiluted": 0.23, "weightedAverageShsOut": 47010309, "weightedAverageShsOutDil": 50109890, "link": "https://www.sec.gov/Archives/edgar/data/859737/000092701696002077/0000927016-96-002077-index.html", "finalLink": "https://www.sec.gov/Archives/edgar/data/859737/", "calculatedOtherExpenses": -6400000, "calculatedOperatingExpenses": 35700000, "calculatedNetInterest": 0, "calculatedOtherIncome": 5000000, "calculatedIncomeNonControlling": 0, "calculatedEbitda": 13000000}, {"date": "1995-09-30", "symbol": "HOLX", "reportedCurrency": "USD", "cik": "0000859737", "fillingDate": "1995-12-26", "acceptedDate": "1995-12-26 00:00:00", "calendarYear": "1995", "period": "FY", "revenue": 43400000, "costOfRevenue": 21500000, "grossProfit": 21900000, "grossProfitRatio": 0.5046082949, "researchAndDevelopmentExpenses": 4300000, "generalAndAdministrativeExpenses": 0, "sellingAndMarketingExpenses": 0, "sellingGeneralAndAdministrativeExpenses": 12300000, "otherExpenses": 0, "operatingExpenses": 17200000, "costAndExpenses": 38700000, "interestIncome": 0, "interestExpense": 0, "depreciationAndAmortization": 600000, "ebitda": 7500000, "ebitdaratio": 0.1728110599, "operatingIncome": 4700000, "operatingIncomeRatio": 0.1082949309, "totalOtherIncomeExpensesNet": -2200000, "incomeBeforeTax": 2600000, "incomeBeforeTaxRatio": 0.0599078341, "incomeTaxExpense": 700000, "netIncome": 1900000, "netIncomeRatio": 0.0437788018, "eps": 0.0538, "epsdiluted": 0.0513, "weightedAverageShsOut": 35007040, "weightedAverageShsOutDil": 36603408, "link": "https://www.sec.gov/Archives/edgar/data/859737/000095010995005384/0000950109-95-005384-index.html", "finalLink": "https://www.sec.gov/Archives/edgar/data/859737/", "calculatedOtherExpenses": 600000, "calculatedOperatingExpenses": 17200000, "calculatedNetInterest": 0, "calculatedOtherIncome": -2100000, "calculatedIncomeNonControlling": 0, "calculatedEbitda": 5300000}, {"date": "1994-09-30", "symbol": "HOLX", "reportedCurrency": "USD", "cik": "0000859737", "fillingDate": "1994-09-30", "acceptedDate": "1994-09-29 20:00:00", "calendarYear": "1994", "period": "FY", "revenue": 38500000, "costOfRevenue": 20300000, "grossProfit": 18200000, "grossProfitRatio": 0.4727272727, "researchAndDevelopmentExpenses": 3400000, "generalAndAdministrativeExpenses": 0, "sellingAndMarketingExpenses": 0, "sellingGeneralAndAdministrativeExpenses": 10100000, "otherExpenses": 0, "operatingExpenses": 14100000, "costAndExpenses": 34400000, "interestIncome": 0, "interestExpense": 0, "depreciationAndAmortization": 600000, "ebitda": 4500000, "ebitdaratio": 0.1168831169, "operatingIncome": 4100000, "operatingIncomeRatio": 0.1064935065, "totalOtherIncomeExpensesNet": 200000, "incomeBeforeTax": 4300000, "incomeBeforeTaxRatio": 0.1116883117, "incomeTaxExpense": 1300000, "netIncome": 3000000, "netIncomeRatio": 0.0779220779, "eps": 0.12, "epsdiluted": 0.12, "weightedAverageShsOut": 24489796, "weightedAverageShsOutDil": 24489796, "link": null, "finalLink": null, "calculatedOtherExpenses": 600000, "calculatedOperatingExpenses": 14100000, "calculatedNetInterest": 0, "calculatedOtherIncome": 200000, "calculatedIncomeNonControlling": 0, "calculatedEbitda": 4700000}, {"date": "1993-09-30", "symbol": "HOLX", "reportedCurrency": "USD", "cik": "0000859737", "fillingDate": "1993-09-30", "acceptedDate": "1993-09-29 20:00:00", "calendarYear": "1993", "period": "FY", "revenue": 24800000, "costOfRevenue": 13300000, "grossProfit": 11500000, "grossProfitRatio": 0.4637096774, "researchAndDevelopmentExpenses": 0, "generalAndAdministrativeExpenses": 0, "sellingAndMarketingExpenses": 0, "sellingGeneralAndAdministrativeExpenses": 13100000, "otherExpenses": 0, "operatingExpenses": 13500000, "costAndExpenses": 26800000, "interestIncome": 0, "interestExpense": 0, "depreciationAndAmortization": 400000, "ebitda": -1900000, "ebitdaratio": -0.0766129032, "operatingIncome": -2000000, "operatingIncomeRatio": -0.0806451613, "totalOtherIncomeExpensesNet": 300000, "incomeBeforeTax": -2100000, "incomeBeforeTaxRatio": -0.0846774194, "incomeTaxExpense": -300000, "netIncome": -1800000, "netIncomeRatio": -0.0725806452, "eps": -0.0575, "epsdiluted": -0.0575, "weightedAverageShsOut": 31304348, "weightedAverageShsOutDil": 31304348, "link": null, "finalLink": null, "calculatedOtherExpenses": 400000, "calculatedOperatingExpenses": 13500000, "calculatedNetInterest": 0, "calculatedOtherIncome": -100000, "calculatedIncomeNonControlling": 0, "calculatedEbitda": -1600000}, {"date": "1992-09-30", "symbol": "HOLX", "reportedCurrency": "USD", "cik": "0000859737", "fillingDate": "1992-09-30", "acceptedDate": "1992-09-29 20:00:00", "calendarYear": "1992", "period": "FY", "revenue": 26200000, "costOfRevenue": 13200000, "grossProfit": 13000000, "grossProfitRatio": 0.4961832061, "researchAndDevelopmentExpenses": 0, "generalAndAdministrativeExpenses": 0, "sellingAndMarketingExpenses": 0, "sellingGeneralAndAdministrativeExpenses": 11400000, "otherExpenses": 0, "operatingExpenses": 11700000, "costAndExpenses": 24900000, "interestIncome": 0, "interestExpense": 0, "depreciationAndAmortization": 300000, "ebitda": 800000, "ebitdaratio": 0.0305343511, "operatingIncome": 1300000, "operatingIncomeRatio": 0.0496183206, "totalOtherIncomeExpensesNet": 800000, "incomeBeforeTax": 2100000, "incomeBeforeTaxRatio": 0.0801526718, "incomeTaxExpense": 600000, "netIncome": 1500000, "netIncomeRatio": 0.0572519084, "eps": 0.0475, "epsdiluted": 0.0475, "weightedAverageShsOut": 31578947, "weightedAverageShsOutDil": 31578947, "link": null, "finalLink": null, "calculatedOtherExpenses": 300000, "calculatedOperatingExpenses": 11700000, "calculatedNetInterest": 0, "calculatedOtherIncome": 800000, "calculatedIncomeNonControlling": 0, "calculatedEbitda": 1600000}, {"date": "1991-09-30", "symbol": "HOLX", "reportedCurrency": "USD", "cik": "0000859737", "fillingDate": "1991-09-30", "acceptedDate": "1991-09-29 20:00:00", "calendarYear": "1991", "period": "FY", "revenue": 17100000, "costOfRevenue": 8200000, "grossProfit": 8900000, "grossProfitRatio": 0.5204678363, "researchAndDevelopmentExpenses": 0, "generalAndAdministrativeExpenses": 0, "sellingAndMarketingExpenses": 0, "sellingGeneralAndAdministrativeExpenses": 8400000, "otherExpenses": 0, "operatingExpenses": 8700000, "costAndExpenses": 16900000, "interestIncome": 0, "interestExpense": 0, "depreciationAndAmortization": 300000, "ebitda": -300000, "ebitdaratio": -0.0175438596, "operatingIncome": 200000, "operatingIncomeRatio": 0.0116959064, "totalOtherIncomeExpensesNet": 800000, "incomeBeforeTax": 1000000, "incomeBeforeTaxRatio": 0.0584795322, "incomeTaxExpense": 300000, "netIncome": 700000, "netIncomeRatio": 0.0409356725, "eps": 0.0225, "epsdiluted": 0.0225, "weightedAverageShsOut": 31111111, "weightedAverageShsOutDil": 31111111, "link": null, "finalLink": null, "calculatedOtherExpenses": 300000, "calculatedOperatingExpenses": 8700000, "calculatedNetInterest": 0, "calculatedOtherIncome": 800000, "calculatedIncomeNonControlling": 0, "calculatedEbitda": 500000}, {"date": "1990-09-30", "symbol": "HOLX", "reportedCurrency": "USD", "cik": "0000859737", "fillingDate": "1990-09-30", "acceptedDate": "1990-09-29 20:00:00", "calendarYear": "1990", "period": "FY", "revenue": 19800000, "costOfRevenue": 9200000, "grossProfit": 10600000, "grossProfitRatio": 0.5353535354, "researchAndDevelopmentExpenses": 0, "generalAndAdministrativeExpenses": 0, "sellingAndMarketingExpenses": 0, "sellingGeneralAndAdministrativeExpenses": 7200000, "otherExpenses": 0, "operatingExpenses": 7400000, "costAndExpenses": 16600000, "interestIncome": 0, "interestExpense": 0, "depreciationAndAmortization": 200000, "ebitda": 2800000, "ebitdaratio": 0.1414141414, "operatingIncome": 3200000, "operatingIncomeRatio": 0.1616161616, "totalOtherIncomeExpensesNet": 600000, "incomeBeforeTax": 3700000, "incomeBeforeTaxRatio": 0.1868686869, "incomeTaxExpense": 1100000, "netIncome": 2600000, "netIncomeRatio": 0.1313131313, "eps": 0.0925, "epsdiluted": 0.0925, "weightedAverageShsOut": 28108108, "weightedAverageShsOutDil": 28108108, "link": null, "finalLink": null, "calculatedOtherExpenses": 200000, "calculatedOperatingExpenses": 7400000, "calculatedNetInterest": 0, "calculatedOtherIncome": 500000, "calculatedIncomeNonControlling": 0, "calculatedEbitda": 3400000}, {"date": "1989-09-30", "symbol": "HOLX", "reportedCurrency": "USD", "cik": "0000859737", "fillingDate": "1989-09-30", "acceptedDate": "1989-09-29 20:00:00", "calendarYear": "1989", "period": "FY", "revenue": 11400000, "costOfRevenue": 4100000, "grossProfit": 7300000, "grossProfitRatio": 0.6403508772, "researchAndDevelopmentExpenses": 0, "generalAndAdministrativeExpenses": 0, "sellingAndMarketingExpenses": 0, "sellingGeneralAndAdministrativeExpenses": 5500000, "otherExpenses": 0, "operatingExpenses": 5600000, "costAndExpenses": 9700000, "interestIncome": 0, "interestExpense": 0, "depreciationAndAmortization": 100000, "ebitda": 1700000, "ebitdaratio": 0.149122807, "operatingIncome": 1700000, "operatingIncomeRatio": 0.149122807, "totalOtherIncomeExpensesNet": 100000, "incomeBeforeTax": 1700000, "incomeBeforeTaxRatio": 0.149122807, "incomeTaxExpense": 300000, "netIncome": 1400000, "netIncomeRatio": 0.1228070175, "eps": 0.065, "epsdiluted": 0.06, "weightedAverageShsOut": 8712000, "weightedAverageShsOutDil": 8712000, "link": null, "finalLink": null, "calculatedOtherExpenses": 100000, "calculatedOperatingExpenses": 5600000, "calculatedNetInterest": 0, "calculatedOtherIncome": 0, "calculatedIncomeNonControlling": 0, "calculatedEbitda": 1800000}]}